__init__.py
example/__init__.py
example/example.py
stoma-0.1.0.dist-info/licenses/LICENSE
stoma-0.1.0.dist-info/METADATA
stoma-0.1.0.dist-info/WHEEL
stoma-0.1.0.dist-info/top_level.txt
stoma-0.1.0.dist-info/RECORD
