Metadata-Version: 2.4
Name: stoma
Version: 0.1.0
Summary: An interface automation testing framework inspired by FastAPI.
Requires-Python: >=3.13
License-File: LICENSE
Requires-Dist: pytest>=8.4.2
Requires-Dist: requests>=2.32.5
Dynamic: license-file
